loganmatic/__init__.py
loganmatic-0.0.16.dist-info/LICENSE
loganmatic-0.0.16.dist-info/METADATA
loganmatic-0.0.16.dist-info/WHEEL
loganmatic-0.0.16.dist-info/top_level.txt
loganmatic-0.0.16.dist-info/RECORD
