Metadata-Version: 2.1
Name: loganmatic
Version: 0.0.16
Summary: Loganmatic package
Author: Gabriel Logan
Project-URL: Homepage, https://github.com/gabriel-logan/Math_Lib/tree/main/packages/python
Project-URL: Bug Tracker, https://github.com/gabriel-logan/Math_Lib/tree/main/packages/python
Classifier: Programming Language :: Python :: 3
Classifier: License :: OSI Approved :: MIT License
Classifier: Operating System :: OS Independent
Requires-Python: >=3.7
License-File: LICENSE
